FHIL_python_utils/__init__.py
FHIL_python_utils/_version.py
FHIL_python_utils/plotting/__init__.py
FHIL_python_utils/plotting/anndata_gridplot.py
FHIL_python_utils/plotting/confusion_matrix_plot.py
FHIL_python_utils/plotting/rotate_x_axis_labels.py
FHIL_python_utils/sc/__init__.py
FHIL_python_utils/sc/daniel_processing.py
FHIL_python_utils/sc/multi_object_embedding_scatter.py
FHIL_python_utils/sc/nmad_filter.py
FHIL_python_utils/sc/ridge_plot.py
FHIL_python_utils/spatial/SpatialLassoManager.py
FHIL_python_utils/spatial/__init__.py
FHIL_python_utils/spatial/multi_object_spatial_scatter.py
FHIL_python_utils/svm/__init__.py
FHIL_python_utils/svm/annotate_clusters_by_consensus.py
FHIL_python_utils/svm/classes_from_probability_matrix.py
FHIL_python_utils/svm/confusion_bubble_matrix.py
FHIL_python_utils/svm/feature_weight_heatmap.py
fhil_python_utils-0.3.3.dist-info/licenses/LICENSE
fhil_python_utils-0.3.3.dist-info/METADATA
fhil_python_utils-0.3.3.dist-info/WHEEL
fhil_python_utils-0.3.3.dist-info/top_level.txt
fhil_python_utils-0.3.3.dist-info/RECORD
